lazaro/__init__.py
lazaro/agents/__init__.py
lazaro/agents/a2c.py
lazaro/agents/double_dqn.py
lazaro/agents/double_dueling_dqn.py
lazaro/agents/dqn.py
lazaro/agents/dueling_dqn.py
lazaro/agents/monte_carlo_advantage_actor_critic.py
lazaro/agents/ppo.py
lazaro/agents/base/__init__.py
lazaro/agents/base/base_agent.py
lazaro/agents/base/base_object.py
lazaro/agents/base/models.py
lazaro/agents/explorers/__init__.py
lazaro/agents/explorers/noisy_explorer.py
lazaro/agents/explorers/random_explorer.py
lazaro/agents/explorers/base/__init__.py
lazaro/agents/explorers/base/explorer.py
lazaro/agents/explorers/base/params.py
lazaro/agents/explorers/tests/__init__.py
lazaro/agents/explorers/tests/test_noisy_explorer.py
lazaro/agents/explorers/tests/test_random_explorer.py
lazaro/agents/explorers/tests/tools.py
lazaro/agents/interfaces/__init__.py
lazaro/agents/interfaces/agent_events_interface.py
lazaro/agents/interfaces/explorer_interface.py
lazaro/agents/interfaces/replay_buffer_interface.py
lazaro/agents/loggers/__init__.py
lazaro/agents/loggers/tensorboard.py
lazaro/agents/loggers/tensorboard_logger.py
lazaro/agents/replay_buffers/__init__.py
lazaro/agents/replay_buffers/n_steps_priorized_replay_buffer.py
lazaro/agents/replay_buffers/n_steps_random_replay_buffer.py
lazaro/agents/replay_buffers/priorized_replay_buffer.py
lazaro/agents/replay_buffers/random_replay_buffer.py
lazaro/agents/replay_buffers/base/__init__.py
lazaro/agents/replay_buffers/base/n_steps_replay_buffer.py
lazaro/agents/replay_buffers/base/params.py
lazaro/agents/replay_buffers/base/replay_buffer.py
lazaro/agents/replay_buffers/base/segment_trees/__init__.py
lazaro/agents/replay_buffers/base/segment_trees/min_segment_tree.py
lazaro/agents/replay_buffers/base/segment_trees/segment_tree.py
lazaro/agents/replay_buffers/base/segment_trees/sum_segment_tree.py
lazaro/agents/replay_buffers/tests/__init__.py
lazaro/agents/replay_buffers/tests/test_n_steps_prioritized_replay_buffer.py
lazaro-0.1.1.dist-info/LICENSE
lazaro-0.1.1.dist-info/METADATA
lazaro-0.1.1.dist-info/WHEEL
lazaro-0.1.1.dist-info/top_level.txt
lazaro-0.1.1.dist-info/RECORD
