Metadata-Version: 2.1
Name: lazaro
Version: 0.1.1
Summary: Reinforcement learning framework for implementing custom models on custom environments using state of the art RL algorithms
Home-page: https://github.com/GabrielMusat/lazaro
Author: Gabriel Musat
Author-email: gabimtme@gmail.com
License: Apache 2.0
Platform: UNKNOWN
Classifier: Development Status :: 3 - Alpha
Classifier: Environment :: GPU
Classifier: Environment :: GPU :: NVIDIA CUDA
Classifier: Intended Audience :: Developers
Classifier: Intended Audience :: Education
Classifier: Intended Audience :: Science/Research
Classifier: License :: OSI Approved :: Apache Software License
Classifier: Operating System :: MacOS
Classifier: Operating System :: Microsoft :: Windows
Classifier: Operating System :: POSIX
Classifier: Operating System :: Unix
Classifier: Programming Language :: Python :: 3.7
Classifier: Programming Language :: Python :: 3.8
Classifier: Programming Language :: Python :: 3.9
Classifier: Topic :: Scientific/Engineering :: Artificial Intelligence
Classifier: Typing :: Typed
Requires-Python: >=3.7.*
Requires-Dist: gym (>=0.18.0)
Requires-Dist: numpy (>=1.18.0)
Requires-Dist: torch (>=1.7.1)
Requires-Dist: tensorboard (>=2.4.0)
